nsb/__about__.py
nsb/__init__.py
nsb/__main__.py
nsb/brightness.py
nsb/config.py
nsb/fitsimage.py
nsb/help.py
nsb/input_options.py
nsb/model.py
nsb/nsbtools.py
nsb/gaia/__init__.py
nsb/gaia/create.py
nsb/gaia/database_query.py
nsb/gaia/ducaticat.txt
nsb/mypycat/__init__.py
nsb-0.6.0.dist-info/LICENSE.txt
nsb-0.6.0.dist-info/METADATA
nsb-0.6.0.dist-info/WHEEL
nsb-0.6.0.dist-info/entry_points.txt
nsb-0.6.0.dist-info/top_level.txt
nsb-0.6.0.dist-info/RECORD
