Metadata-Version: 2.1
Name: nsb
Version: 0.6.0
Summary: ('Draws nightsky allskymaps',)
Home-page: https://pypi.python.org/pypi/nsb
Author: Matthias Buechele
Author-email: matthias.buechele@fau.de
License: UNKNOWN
Platform: UNKNOWN
Classifier: Development Status :: 4 - Beta
Classifier: Environment :: Console
Classifier: Intended Audience :: Science/Research
Classifier: License :: OSI Approved :: GNU General Public License v3 (GPLv3)
Classifier: Operating System :: POSIX :: Linux
Classifier: Topic :: Scientific/Engineering :: Astronomy
Classifier: Topic :: Scientific/Engineering :: Atmospheric Science
Classifier: Topic :: Scientific/Engineering :: Physics
Requires-Dist: healpy
Requires-Dist: tqdm
Requires-Dist: ephem
Requires-Dist: astropy
Requires-Dist: scipy
Requires-Dist: numpy
Requires-Dist: matplotlib
